commweb/__init__.py
commweb/cartridge_hook.py
commweb/exc.py
commweb/purchase.py
commweb/response.py
commweb/test/__init__.py
commweb/test/test_responses.py
django_commweb-0.3.3.dist-info/DESCRIPTION.rst
django_commweb-0.3.3.dist-info/METADATA
django_commweb-0.3.3.dist-info/RECORD
django_commweb-0.3.3.dist-info/WHEEL
django_commweb-0.3.3.dist-info/metadata.json
django_commweb-0.3.3.dist-info/top_level.txt
