Metadata-Version: 2.0
Name: django-commweb
Version: 0.3.3
Summary: Django module for interfacing with the CommWeb merchant gateway.
Home-page: https://github.com/sjkingo/django-commweb
Author: Sam Kingston
Author-email: sam@sjkwi.com.au
License: BSD License
Platform: UNKNOWN
Classifier: Programming Language :: Python
Classifier: Programming Language :: Python :: 2.7
Classifier: Programming Language :: Python :: 3.4
Classifier: Environment :: Web Environment
Classifier: License :: OSI Approved :: BSD License
Classifier: Operating System :: OS Independent
Classifier: Topic :: Software Development :: Libraries :: Python Modules
Classifier: Framework :: Django
Requires-Dist: Django (>=1.5)
Requires-Dist: requests
